AUTHORS
LICENSE
MANIFEST.in
README.md
setup.py
admin_adv_search_builder/__init__.py
admin_adv_search_builder/apps.py
admin_adv_search_builder/filters.py
admin_adv_search_builder/tests.py
admin_adv_search_builder/migrations/__init__.py
admin_adv_search_builder/templates/filters/custom_search.html
django_admin_search_builder.egg-info/PKG-INFO
django_admin_search_builder.egg-info/SOURCES.txt
django_admin_search_builder.egg-info/dependency_links.txt
django_admin_search_builder.egg-info/requires.txt
django_admin_search_builder.egg-info/top_level.txt