Metadata-Version: 2.1
Name: django-admin-search-builder
Version: 0.2.2
Summary: Django Admin Search Builder
Home-page: https://github.com/UniversitaDellaCalabria/django-admin-search-builder
Author: Giuseppe De Marco
Author-email: giuseppe.demarco@unical.it
License: Apache Software License
Platform: UNKNOWN
Classifier: Environment :: Web Environment
Classifier: Framework :: Django
Classifier: Framework :: Django :: 2.0
Classifier: Framework :: Django :: 3.0
Classifier: Intended Audience :: Developers
Classifier: License :: OSI Approved :: Apache Software License
Classifier: Operating System :: OS Independent
Classifier: Programming Language :: Python
Classifier: Programming Language :: Python :: 3
